{
  "Headers": [
    {
      "AboveBlockID": 51,
      "LabelText": "Clusters"
    },
    {
      "AboveBlockID": 18,
      "LabelText": "Small Clusters"
    },
    {
      "AboveBlockID": 40,
      "LabelText": "Surge"
    },
    {
      "AboveBlockID": 59,
      "LabelText": "Bulkhead"
    },
    {
      "AboveBlockID": 67,
      "LabelText": "Error trickles"
    },
    {
      "AboveBlockID": 4,
      "LabelText": "No Alarm"
    },
    {
      "AboveBlockID": 10,
      "LabelText": "Reserved Scans"
    },
    {
      "AboveBlockID": 7,
      "LabelText": "Singles"
    },
    {
      "AboveBlockID": 91,
      "LabelText": "Mixed Irregular (All types)"
    },
    {
      "AboveBlockID": 5,
      "LabelText": "Mixed Regulars (Reds and Orange)"
    },
    {
      "AboveBlockID": 121,
      "LabelText": "Sustained"
    }
  ],
    "Blocks": [
        {
            "PublicAlarmName": "Scan",
            "TriggerAlarmOnActivate": false,
            "SurvivalWaveSettings": 0,
            "SurvivalWavePopulation": 0,
            "SurvivalWaveAreaDistance": 2,
            "DisableSurvivalWaveOnComplete": true,
            "UseRandomPositions": false,
            "WantedDistanceFromStartPos": 0.0,
            "WantedDistanceBetweenPuzzleComponents": 1.0,
            "ChainedPuzzle": [
                {
                    "PuzzleType": 6
                }
            ],
            "OnlyShowHUDWhenPlayerIsClose": false,
            "AlarmSoundStart": 3339129407,
            "AlarmSoundStop": 42633153,
            "name": "Single x1",
            "internalEnabled": true,
            "persistentID": 4
        },
        {
            "PublicAlarmName": "Scan",
            "TriggerAlarmOnActivate": false,
            "SurvivalWaveSettings": 0,
            "SurvivalWavePopulation": 0,
            "SurvivalWaveAreaDistance": 2,
            "DisableSurvivalWaveOnComplete": true,
            "UseRandomPositions": false,
            "WantedDistanceFromStartPos": 0.0,
            "WantedDistanceBetweenPuzzleComponents": 1.0,
            "ChainedPuzzle": [
                {
                    "PuzzleType": 6
                }
            ],
            "OnlyShowHUDWhenPlayerIsClose": false,
            "AlarmSoundStart": 3339129407,
            "AlarmSoundStop": 42633153,
            "name": "Single x1",
            "internalEnabled": true,
            "persistentID": 11
        },
        {
            "PublicAlarmName": "FlashScan",
            "TriggerAlarmOnActivate": false,
            "SurvivalWaveSettings": 0,
            "SurvivalWavePopulation": 0,
            "SurvivalWaveAreaDistance": 2,
            "DisableSurvivalWaveOnComplete": true,
            "UseRandomPositions": false,
            "WantedDistanceFromStartPos": 0.0,
            "WantedDistanceBetweenPuzzleComponents": 1.0,
            "ChainedPuzzle": [
                {
                    "PuzzleType": 105
                }
            ],
            "OnlyShowHUDWhenPlayerIsClose": false,
            "AlarmSoundStart": 3339129407,
            "AlarmSoundStop": 42633153,
            "name": "Single x1",
            "internalEnabled": true,
            "persistentID": 105
        },
        {
            "PublicAlarmName": "Class 3 Alarm",
            "TriggerAlarmOnActivate": true,
            "SurvivalWaveSettings": 1,
            "SurvivalWavePopulation": 1,
            "SurvivalWaveAreaDistance": 1,
            "DisableSurvivalWaveOnComplete": true,
            "UseRandomPositions": false,
            "WantedDistanceFromStartPos": 25.0,
            "WantedDistanceBetweenPuzzleComponents": 50.0,
            "ChainedPuzzle": [
                {
                    "PuzzleType": 6
                },
                {
                    "PuzzleType": 2
                },
                {
                    "PuzzleType": 6
                }
            ],
            "OnlyShowHUDWhenPlayerIsClose": false,
            "AlarmSoundStart": 3339129407,
            "AlarmSoundStop": 42633153,
            "name": "StandardAlarm",
            "internalEnabled": true,
            "persistentID": 5
        },
        {
            "PublicAlarmName": "Class 4 Cluster Surge",
            "TriggerAlarmOnActivate": true,
            "SurvivalWaveSettings": 2,
            "SurvivalWavePopulation": 1,
            "SurvivalWaveAreaDistance": 2,
            "DisableSurvivalWaveOnComplete": false,
            "UseRandomPositions": false,
            "WantedDistanceFromStartPos": 25.0,
            "WantedDistanceBetweenPuzzleComponents": 50.0,
            "ChainedPuzzle": [
                {
                    "PuzzleType": 9
                },
                {
                    "PuzzleType": 9
                },
                {
                    "PuzzleType": 9
                },
                {
                    "PuzzleType": 16
                }
            ],
            "OnlyShowHUDWhenPlayerIsClose": false,
            "AlarmSoundStart": 3339129407,
            "AlarmSoundStop": 42633153,
            "name": "StandardSurge",
            "internalEnabled": true,
            "persistentID": 6
        },
        {
            "PublicAlarmName": "Scan",
            "TriggerAlarmOnActivate": false,
            "SurvivalWaveSettings": 0,
            "SurvivalWavePopulation": 0,
            "SurvivalWaveAreaDistance": 2,
            "DisableSurvivalWaveOnComplete": true,
            "UseRandomPositions": false,
            "WantedDistanceFromStartPos": 0.0,
            "WantedDistanceBetweenPuzzleComponents": 1.0,
            "ChainedPuzzle": [
                {
                    "PuzzleType": 6
                }
            ],
            "OnlyShowHUDWhenPlayerIsClose": true,
            "AlarmSoundStart": 3339129407,
            "AlarmSoundStop": 42633153,
            "name": "Single x1_No_close_HUD",
            "internalEnabled": true,
            "persistentID": 173
        },
        {
            "PublicAlarmName": "Scan",
            "TriggerAlarmOnActivate": false,
            "SurvivalWaveSettings": 0,
            "SurvivalWavePopulation": 0,
            "SurvivalWaveAreaDistance": 2,
            "DisableSurvivalWaveOnComplete": true,
            "UseRandomPositions": false,
            "WantedDistanceFromStartPos": 0.0,
            "WantedDistanceBetweenPuzzleComponents": 1.0,
            "ChainedPuzzle": [
                {
                    "PuzzleType": 2
                }
            ],
            "OnlyShowHUDWhenPlayerIsClose": false,
            "AlarmSoundStart": 3339129407,
            "AlarmSoundStop": 42633153,
            "name": "Single red x1 No alarm",
            "internalEnabled": true,
            "persistentID": 137
        },
        {
            "PublicAlarmName": "MovingScan",
            "TriggerAlarmOnActivate": false,
            "SurvivalWaveSettings": 0,
            "SurvivalWavePopulation": 0,
            "SurvivalWaveAreaDistance": 2,
            "DisableSurvivalWaveOnComplete": true,
            "UseRandomPositions": false,
            "WantedDistanceFromStartPos": 0.0,
            "WantedDistanceBetweenPuzzleComponents": 1.0,
            "ChainedPuzzle": [
                {
                    "PuzzleType": 130
                }
            ],
            "OnlyShowHUDWhenPlayerIsClose": false,
            "AlarmSoundStart": 3339129407,
            "AlarmSoundStop": 42633153,
            "name": "Single red x1 No alarm",
            "internalEnabled": true,
            "persistentID": 150
        },
        {
            "PublicAlarmName": "Surge Error",
            "TriggerAlarmOnActivate": true,
            "SurvivalWaveSettings": 2,
            "SurvivalWavePopulation": 1,
            "SurvivalWaveAreaDistance": 2,
            "DisableSurvivalWaveOnComplete": false,
            "UseRandomPositions": false,
            "WantedDistanceFromStartPos": 0.0,
            "WantedDistanceBetweenPuzzleComponents": 0.0,
            "ChainedPuzzle": [
                {
                    "PuzzleType": 6
                }
            ],
            "OnlyShowHUDWhenPlayerIsClose": false,
            "AlarmSoundStart": 3339129407,
            "AlarmSoundStop": 42633153,
            "name": "StandardAlarm",
            "internalEnabled": true,
            "persistentID": 7
        },
        {
            "PublicAlarmName": "Regualer Error",
            "TriggerAlarmOnActivate": true,
            "SurvivalWaveSettings": 4,
            "SurvivalWavePopulation": 1,
            "SurvivalWaveAreaDistance": 2,
            "DisableSurvivalWaveOnComplete": false,
            "UseRandomPositions": false,
            "WantedDistanceFromStartPos": 0.0,
            "WantedDistanceBetweenPuzzleComponents": 0.0,
            "ChainedPuzzle": [
                {
                    "PuzzleType": 6
                }
            ],
            "OnlyShowHUDWhenPlayerIsClose": false,
            "AlarmSoundStart": 3339129407,
            "AlarmSoundStop": 42633153,
            "name": "StandardAlarm",
            "internalEnabled": true,
            "persistentID": 8
        },
        {
            "PublicAlarmName": "Class 6 Alarm",
            "TriggerAlarmOnActivate": true,
            "SurvivalWaveSettings": 1,
            "SurvivalWavePopulation": 1,
            "SurvivalWaveAreaDistance": 2,
            "DisableSurvivalWaveOnComplete": true,
            "UseRandomPositions": false,
            "WantedDistanceFromStartPos": 0.0,
            "WantedDistanceBetweenPuzzleComponents": 30.0,
            "ChainedPuzzle": [
                {
                    "PuzzleType": 9
                },
                {
                    "PuzzleType": 6
                },
                {
                    "PuzzleType": 9
                },
                {
                    "PuzzleType": 6
                },
                {
                    "PuzzleType": 9
                },
                {
                    "PuzzleType": 6
                }
            ],
            "OnlyShowHUDWhenPlayerIsClose": false,
            "AlarmSoundStart": 3339129407,
            "AlarmSoundStop": 42633153,
            "name": "StandardAlarm",
            "internalEnabled": true,
            "persistentID": 9
        },
        {
            "PublicAlarmName": "Regualer Error",
            "TriggerAlarmOnActivate": true,
            "SurvivalWaveSettings": 6,
            "SurvivalWavePopulation": 1,
            "SurvivalWaveAreaDistance": 2,
            "DisableSurvivalWaveOnComplete": false,
            "UseRandomPositions": false,
            "WantedDistanceFromStartPos": 0.0,
            "WantedDistanceBetweenPuzzleComponents": 0.0,
            "ChainedPuzzle": [
                {
                    "PuzzleType": 6
                }
            ],
            "OnlyShowHUDWhenPlayerIsClose": false,
            "AlarmSoundStart": 3339129407,
            "AlarmSoundStop": 42633153,
            "name": "StandardAlarm",
            "internalEnabled": true,
            "persistentID": 10
        },
        {
            "PublicAlarmName": "RoomSCAN",
            "TriggerAlarmOnActivate": true,
            "SurvivalWaveSettings": 1,
            "SurvivalWavePopulation": 1,
            "SurvivalWaveAreaDistance": 2,
            "DisableSurvivalWaveOnComplete": false,
            "UseRandomPositions": false,
            "WantedDistanceFromStartPos": 0.0,
            "WantedDistanceBetweenPuzzleComponents": 0.0,
            "ChainedPuzzle": [
                {
                    "PuzzleType": 36
                }
            ],
            "OnlyShowHUDWhenPlayerIsClose": false,
            "AlarmSoundStart": 3339129407,
            "AlarmSoundStop": 42633153,
            "name": "StandardAlarm",
            "internalEnabled": true,
            "persistentID": 11
        },
        {
            "PublicAlarmName": "Class sus 6 Alarm",
            "TriggerAlarmOnActivate": true,
            "SurvivalWaveSettings": 1,
            "SurvivalWavePopulation": 1,
            "SurvivalWaveAreaDistance": 2,
            "DisableSurvivalWaveOnComplete": false,
            "UseRandomPositions": false,
            "WantedDistanceFromStartPos": 30.0,
            "WantedDistanceBetweenPuzzleComponents": 60.0,
            "ChainedPuzzle": [
                {
                    "PuzzleType": 6
                },
                {
                    "PuzzleType": 9
                },
                {
                    "PuzzleType": 6
                },
                {
                    "PuzzleType": 2
                },
                {
                    "PuzzleType": 2
                },
                {
                    "PuzzleType": 6
                }
            ],
            "OnlyShowHUDWhenPlayerIsClose": false,
            "AlarmSoundStart": 3339129407,
            "AlarmSoundStop": 42633153,
            "name": "StandardAlarm",
            "internalEnabled": true,
            "persistentID": 12
        }
    ],
  "LastPersistentID": 193
}